prompt2model/__init__.py
prompt2model/run_locally.py
prompt2model/version.py
prompt2model/dataset_generator/__init__.py
prompt2model/dataset_generator/base.py
prompt2model/dataset_generator/mock.py
prompt2model/dataset_generator/prompt_based.py
prompt2model/dataset_generator/prompt_template.py
prompt2model/dataset_processor/__init__.py
prompt2model/dataset_processor/base.py
prompt2model/dataset_processor/mock.py
prompt2model/dataset_processor/textualize.py
prompt2model/dataset_retriever/__init__.py
prompt2model/dataset_retriever/base.py
prompt2model/dataset_retriever/column_selection_prompt.py
prompt2model/dataset_retriever/description_dataset_retriever.py
prompt2model/dataset_retriever/mock.py
prompt2model/dataset_retriever/reranking_prompt.py
prompt2model/dataset_retriever/run_dataset_retriever.py
prompt2model/dataset_retriever/task_expansion_prompt.py
prompt2model/dataset_transformer/__init__.py
prompt2model/dataset_transformer/base.py
prompt2model/dataset_transformer/prompt_based.py
prompt2model/dataset_transformer/prompt_template.py
prompt2model/demo_creator/__init__.py
prompt2model/demo_creator/create.py
prompt2model/demo_creator/mock.py
prompt2model/model_evaluator/__init__.py
prompt2model/model_evaluator/base.py
prompt2model/model_evaluator/mock.py
prompt2model/model_evaluator/seq2seq.py
prompt2model/model_executor/__init__.py
prompt2model/model_executor/base.py
prompt2model/model_executor/generate.py
prompt2model/model_executor/mock.py
prompt2model/model_retriever/__init__.py
prompt2model/model_retriever/base.py
prompt2model/model_retriever/description_based_retriever.py
prompt2model/model_retriever/generate_hypothetical_document.py
prompt2model/model_retriever/mock.py
prompt2model/model_retriever/run_model_retriever.py
prompt2model/model_trainer/__init__.py
prompt2model/model_trainer/base.py
prompt2model/model_trainer/callback.py
prompt2model/model_trainer/generate.py
prompt2model/model_trainer/mock.py
prompt2model/model_trainer/qlora_trainer.py
prompt2model-0.1.0.dist-info/METADATA
prompt2model-0.1.0.dist-info/WHEEL
prompt2model-0.1.0.dist-info/licenses/LICENSE
prompt2model-0.1.0.dist-info/RECORD
