Metadata-Version: 2.3
Name: prompt2model
Version: 0.1.0
Summary: A library for distilling models from prompts.
Author-email: Vijay Viswanathan <vijayv@andrew.cmu.edu>, Chenyang Zhao <zhaochen20@mails.tsinghua.edu.cn>
License:                                  Apache License
License-File: LICENSE
Classifier: Programming Language :: Python :: 3.9
Classifier: Programming Language :: Python :: 3.10
Classifier: Programming Language :: Python :: 3.11
Requires-Python: >=3.9
Requires-Dist: aiolimiter
Requires-Dist: bert-score
Requires-Dist: datasets
Requires-Dist: evaluate
Requires-Dist: faiss-cpu
Requires-Dist: fastapi
Requires-Dist: gradio==3.38.0
Requires-Dist: litellm
Requires-Dist: mdtex2html
Requires-Dist: nest-asyncio
Requires-Dist: openai
Requires-Dist: pandas
Requires-Dist: peft
Requires-Dist: protobuf
Requires-Dist: psutil
Requires-Dist: pyfiglet
Requires-Dist: pytest
Requires-Dist: retriv
Requires-Dist: sacrebleu
Requires-Dist: scikit-learn
Requires-Dist: sentencepiece
Requires-Dist: termcolor
Requires-Dist: tevatron
Requires-Dist: tiktoken
Requires-Dist: torch
Requires-Dist: transformers
Provides-Extra: dev
Requires-Dist: pre-commit; extra == 'dev'
Requires-Dist: pytest; extra == 'dev'
Provides-Extra: test
Requires-Dist: pytest>=6.0.0; extra == 'test'
